[
{"Table_name": ["Apple Inc."], 
"Logo": ["//upload.wikimedia.org/wikipedia/commons/thumb/f/fa/Apple_logo_black.svg/80px-Apple_logo_black.svg.png"], 
"Photo": ["//upload.wikimedia.org/wikipedia/commons/thumb/e/eb/Apple_park_cupertino_2019.jpg/260px-Apple_park_cupertino_2019.jpg"], "Photo_Caption": ["Apple Park", ", the company's headquarters in ", "Cupertino, California", " within ", "Silicon Valley"], "Formerly": ["Apple Computer Company (1976\u20131977)", "Apple Computer, Inc. (1977\u20132007)"], "Type": ["Public"], "Traded_as": ["Nasdaq", ":\u00a0", "AAPL", "Nasdaq-100", " component", "DJIA", " component", "S&P 100", " component", "S&P 500", " component"], 
"ISIN": ["US0378331005"], 
"Industry": ["Consumer electronics", "Software services", "Online services"], 
"Founded": ["April\u00a01, 1976", "; 46 years ago", "\u00a0(", "1976-04-01", ")", " in ", "Los Altos, California", ", U.S."], 
"Founders": ["Steve Jobs", "Steve Wozniak", "Ronald Wayne"], 
"Headquaters": ["1 Apple Park Way", ", ", "Cupertino, California", ", ", "U.S.", ".mw-parser-output .geo-default,.mw-parser-output .geo-dms,.mw-parser-output .geo-dec{display:inline}.mw-parser-output .geo-nondefault,.mw-parser-output .geo-multi-punct{display:none}.mw-parser-output .longitude,.mw-parser-output .latitude{white-space:nowrap}", "37\u00b020\u203206\u2033N", " ", "122\u00b000\u203232\u2033W", "\ufeff / \ufeff", "37.3349\u00b0N 122.0090\u00b0W", "\ufeff / ", "37.3349; -122.0090", "Coordinates", ": ", "37\u00b020\u203206\u2033N", " ", "122\u00b000\u203232\u2033W", "\ufeff / \ufeff", "37.3349\u00b0N 122.0090\u00b0W", "\ufeff / ", "37.3349; -122.0090"], 
"Number_of_locations": ["521 ", "retail stores", "\u00a0(2022)"], 
"Area_Served": ["Worldwide"], 
"Key_People": ["Arthur D. Levinson", " (", "chairman", ")", "Tim Cook", " (", "CEO", ")", "Jeff Williams", " (", "COO", ")"], 
"Products": ["\n", "AirPods", "\n", "Apple Watch", "\n", "iPad", "\n", "iPhone", "\n", "Mac", "\n"], 
"Services": ["\n", "App Store", "\n", "Apple Card", "\n", "Apple Music", "\n", "Apple TV+", "\n", "Apple Pay", "\n"], 
"Revenue": [" ", "US$", "394.33 billion", "\u00a0(2022)"], 
"Operating_income": [" ", "US$119.44 billion", "\u00a0(2022)"], 
"Net_income": [" ", "US$99.80 billion", "\u00a0(2022)"], 
"Total_assets": [" ", "US$352.76 billion", "\u00a0(2022)"], 
"Total_equity": [" ", "US$50.67 billion", "\u00a0(2022)"], 
"Number_of_employees": ["164,000\u00a0(2022)"], 
"Subsidiaries": ["Apple Studios", "Beats Electronics", "Beddit", "Braeburn Capital", "Claris", "Drive.ai", "InVisage Technologies", "Dark Sky (", "Weather (Apple)", ")"], 
"Website": ["apple.com"]}
]